envrx/__init__.py
envrx/envrx.py
envrx/exceptions.py
envrx/utils.py
envrx-0.0.3.dist-info/LICENSE
envrx-0.0.3.dist-info/METADATA
envrx-0.0.3.dist-info/WHEEL
envrx-0.0.3.dist-info/top_level.txt
envrx-0.0.3.dist-info/RECORD
