Metadata-Version: 2.1
Name: envrx
Version: 0.0.3
Summary: A package to manage environment variables with database and custom env file support.
Home-page: https://github.com/Starkgang/envrx
Author: WarnerStark
Author-email: starktechfriday@gmail.com
Keywords: envrx,env,environment,variables,database,mongodb,sql,redis
Classifier: Development Status :: 3 - Alpha
Classifier: Intended Audience :: Developers
Classifier: License :: OSI Approved :: GNU General Public License v3 (GPLv3)
Classifier: Programming Language :: Python :: 3.9
Classifier: Programming Language :: Python :: 3.10
License-File: LICENSE
